app_manager/__init__.py
app_manager/app_manager.py
app_manager/app_structure.py
app_manager/nvinfer_config_parser.py
maker_manager/__init__.py
maker_manager/convert_option.py
maker_manager/maker_manager.py
maker_manager/thread_handler.py
waffle_box/__init__.py
waffle_box/bake_service.py
waffle_box/cli.py
waffle_box/convert_service.py
waffle_box/pull_service.py
waffle_box_exception/__init__.py
waffle_box_exception/waffle_box_exception.py
waffle_box-0.2.0.dist-info/METADATA
waffle_box-0.2.0.dist-info/WHEEL
waffle_box-0.2.0.dist-info/entry_points.txt
waffle_box-0.2.0.dist-info/RECORD
