Metadata-Version: 2.1
Name: waffle-box
Version: 0.2.0
Summary: 
Author: SangHyeukYoon
Author-email: shyoon@snuailab.ai
Requires-Python: >=3.10,<4.0
Classifier: Programming Language :: Python :: 3
Classifier: Programming Language :: Python :: 3.10
Classifier: Programming Language :: Python :: 3.11
Requires-Dist: black (>=23.7.0,<24.0.0)
Requires-Dist: docker (>=6.1.3,<7.0.0)
Requires-Dist: pre-commit (>=3.3.3,<4.0.0)
Requires-Dist: pytest (>=7.4.0,<8.0.0)
Requires-Dist: pytest-html (>=3.2.0,<4.0.0)
Requires-Dist: typer[all] (>=0.9.0,<0.10.0)
